examples/__init__.py
examples/tokenize.py
modmod/__init__.py
modmod/__version__.py
modmod/model.py
modmod/pool.py
modmod-0.2.5.dist-info/METADATA
modmod-0.2.5.dist-info/RECORD
modmod-0.2.5.dist-info/WHEEL
modmod-0.2.5.dist-info/top_level.txt
