Metadata-Version: 2.1
Name: modmod
Version: 0.2.5
Summary: modular models for efficient ML development
Home-page: https://github.com/Remesh/modmod
Author: Nicholas Tietz-Sokolsky
Author-email: me@ntietz.com
License: Apache 2.0
Platform: UNKNOWN
Classifier: License :: OSI Approved :: Apache Software License
Classifier: Intended Audience :: Science/Research
Classifier: Programming Language :: Python
Classifier: Programming Language :: Python :: 3
Classifier: Programming Language :: Python :: 3.6
Classifier: Programming Language :: Python :: Implementation :: CPython
Classifier: Programming Language :: Python :: Implementation :: PyPy
Requires-Python: >=3.6.0
